uniter/Exceptions.py
uniter/Formulas.py
uniter/Formulas.pyi
uniter/Parser.py
uniter/Parser.pyi
uniter/Uniter.py
uniter/Uniter.pyi
uniter/Util.py
uniter/__init__.py
uniter/units/Amount_of_substance.py
uniter/units/Amount_of_substance.pyi
uniter/units/Angle.py
uniter/units/Angle.pyi
uniter/units/Area.py
uniter/units/Area.pyi
uniter/units/Computer_Memory.py
uniter/units/Computer_Memory.pyi
uniter/units/Density.py
uniter/units/Density.pyi
uniter/units/Electric_Current.py
uniter/units/Electric_Current.pyi
uniter/units/Energy.py
uniter/units/Energy.pyi
uniter/units/Length.py
uniter/units/Length.pyi
uniter/units/Luminous_Intensity.py
uniter/units/Luminous_Intensity.pyi
uniter/units/Mass.py
uniter/units/Mass.pyi
uniter/units/Power.py
uniter/units/Power.pyi
uniter/units/Pressure.py
uniter/units/Pressure.pyi
uniter/units/Resistance.py
uniter/units/Resistance.pyi
uniter/units/Speed.py
uniter/units/Speed.pyi
uniter/units/Temperature.py
uniter/units/Temperature.pyi
uniter/units/Time.py
uniter/units/Time.pyi
uniter/units/Voltage.py
uniter/units/Voltage.pyi
uniter/units/Volume.py
uniter/units/Volume.pyi
uniter/units/__init__.py
uniter-1.0.0.dist-info/METADATA
uniter-1.0.0.dist-info/WHEEL
uniter-1.0.0.dist-info/licenses/LICENSE
uniter-1.0.0.dist-info/RECORD
