Metadata-Version: 2.1
Name: uniter
Version: 1.0.0
Summary: Package to handle unit conversion.
Project-URL: Repository, https://github.com/KrazyManJ/uniter
Project-URL: Bug Tracker, https://github.com/KrazyManJ/uniter/issues
Author: KrazyManJ
License-Expression: MIT
License-File: LICENSE
Classifier: License :: OSI Approved :: MIT License
Classifier: Operating System :: OS Independent
Classifier: Programming Language :: Python :: 3
Classifier: Typing :: Typed
Requires-Python: >=3.10
Requires-Dist: sympy>=1.12
